setup.py
infinispan/__init__.py
infinispan/remotecache.py
infinispan/unsigned.py
infinispan.egg-info/PKG-INFO
infinispan.egg-info/SOURCES.txt
infinispan.egg-info/dependency_links.txt
infinispan.egg-info/requires.txt
infinispan.egg-info/top_level.txt