Metadata-Version: 1.0
Name: infinispan
Version: 1.0.0b1
Summary: Native python client for Infinispan, over the Hot Rod wire protocol
Home-page: http://infinispan.org
Author: Galder Zamarreno
Author-email: galder@jboss.org
License: LGPL
Keywords: infinispan hotrod nosql datagrid
Platform: UNKNOWN
Classifier: License :: OSI Approved :: GNU Library or Lesser General Public License (LGPL)
Classifier: Programming Language :: Python
Classifier: Development Status :: 4 - Beta
Classifier: Intended Audience :: Developers
Classifier: Topic :: Software Development :: Libraries :: Python Modules
